{"P3": {"labels": ["\u6559\u7a0b"], "postTitle": "\u7535\u8111\u4f18\u5316\u00b7\u5173\u4e8eWindows10/11\u7684\u4f18\u5316\u96c6\u9526", "postUrl": "post/dian-nao-you-hua-%C2%B7-guan-yu-Windows10-11-de-you-hua-ji-jin.html", "createdDate": "2024-06-26", "dateLabelColor": "#bc4c00"}, "labelColorDict": {"bug": "#d73a4a", "documentation": "#0075ca", "duplicate": "#cfd3d7", "enhancement": "#a2eeef", "good first issue": "#7057ff", "help wanted": "#008672", "invalid": "#e4e669", "question": "#d876e3", "\u6559\u7a0b": "#ffffff"}}